tensorflow_ranking/__init__.py
tensorflow_ranking/extension/__init__.py
tensorflow_ranking/extension/task.py
tensorflow_ranking/extension/premade/__init__.py
tensorflow_ranking/extension/premade/tfrbert_task.py
tensorflow_ranking/python/__init__.py
tensorflow_ranking/python/data.py
tensorflow_ranking/python/estimator.py
tensorflow_ranking/python/feature.py
tensorflow_ranking/python/head.py
tensorflow_ranking/python/losses.py
tensorflow_ranking/python/losses_impl.py
tensorflow_ranking/python/metrics.py
tensorflow_ranking/python/metrics_impl.py
tensorflow_ranking/python/model.py
tensorflow_ranking/python/utils.py
tensorflow_ranking/python/version.py
tensorflow_ranking/python/keras/__init__.py
tensorflow_ranking/python/keras/estimator.py
tensorflow_ranking/python/keras/feature.py
tensorflow_ranking/python/keras/layers.py
tensorflow_ranking/python/keras/losses.py
tensorflow_ranking/python/keras/metrics.py
tensorflow_ranking/python/keras/model.py
tensorflow_ranking/python/keras/network.py
tensorflow_ranking/python/keras/pipeline.py
tensorflow_ranking/python/keras/saved_model.py
tensorflow_ranking/python/keras/strategy_utils.py
tensorflow_ranking/python/keras/utils.py
tensorflow_ranking/python/keras/canned/__init__.py
tensorflow_ranking/python/keras/canned/dnn.py
tensorflow_ranking/python/keras/canned/gam.py
tensorflow_ranking-0.5.5.dist-info/METADATA
tensorflow_ranking-0.5.5.dist-info/WHEEL
tensorflow_ranking-0.5.5.dist-info/top_level.txt
tensorflow_ranking-0.5.5.dist-info/RECORD
