Metadata-Version: 2.1
Name: tensorflow-ranking
Version: 0.5.5
Summary: Pip package setup file for TensorFlow Ranking.
Home-page: https://github.com/tensorflow/ranking
Author: Google Inc.
Author-email: packages@tensorflow.org
License: Apache 2.0
Keywords: tensorflow ranking learning-to-rank
Classifier: Development Status :: 5 - Production/Stable
Classifier: Intended Audience :: Developers
Classifier: Intended Audience :: Education
Classifier: Intended Audience :: Science/Research
Classifier: License :: OSI Approved :: Apache Software License
Classifier: Programming Language :: Python :: 2
Classifier: Programming Language :: Python :: 2.7
Classifier: Programming Language :: Python :: 3
Classifier: Programming Language :: Python :: 3.4
Classifier: Programming Language :: Python :: 3.5
Classifier: Programming Language :: Python :: 3.6
Classifier: Topic :: Scientific/Engineering
Classifier: Topic :: Scientific/Engineering :: Mathematics
Classifier: Topic :: Scientific/Engineering :: Artificial Intelligence
Classifier: Topic :: Software Development
Classifier: Topic :: Software Development :: Libraries
Classifier: Topic :: Software Development :: Libraries :: Python Modules
Requires-Dist: absl-py >=0.1.6
Requires-Dist: numpy >=1.23.2
Requires-Dist: six >=1.10.0
Requires-Dist: tensorflow-serving-api <3.0.0,>=2.0.0
Requires-Dist: tensorflow <2.16.0
